Metadata-Version: 2.4
Name: apolo-extras
Version: 25.9.0
Home-page: https://github.com/neuro-inc/neuro-extras
Requires-Python: >=3.9.0
License-File: LICENSE
Requires-Dist: apolo-cli>=25.8.1
Requires-Dist: click>=8.0
Requires-Dist: toml>=0.10.0
Requires-Dist: pyyaml>=6.0
Dynamic: home-page
Dynamic: license-file
Dynamic: requires-dist
Dynamic: requires-python
